plover_stroke_counter/__init__.py
plover_stroke_counter-0.1.0.dist-info/METADATA
plover_stroke_counter-0.1.0.dist-info/WHEEL
plover_stroke_counter-0.1.0.dist-info/entry_points.txt
plover_stroke_counter-0.1.0.dist-info/top_level.txt
plover_stroke_counter-0.1.0.dist-info/zip-safe
plover_stroke_counter-0.1.0.dist-info/RECORD
